cronusalert/__init__.py
cronusalert/client.py
cronusalert-0.1.0.dist-info/METADATA
cronusalert-0.1.0.dist-info/WHEEL
cronusalert-0.1.0.dist-info/top_level.txt
cronusalert-0.1.0.dist-info/RECORD
