Metadata-Version: 2.1
Name: cronusalert
Version: 0.1.0
Summary: A Python client for Cronus alerts
Home-page: https://github.com/mperkins8080/cronus-alert/python/cronusalert
Author: Mathew Perkins
Author-email: 57matperkins57@gmail.com
Classifier: Programming Language :: Python :: 3
Classifier: License :: OSI Approved :: MIT License
Classifier: Operating System :: OS Independent
Requires-Python: >=3.6
